jetconf/__init__.py
jetconf/__main__.py
jetconf/config.py
jetconf/data.py
jetconf/errors.py
jetconf/handler_base.py
jetconf/handler_list.py
jetconf/helpers.py
jetconf/http_handlers.py
jetconf/jetconf.py
jetconf/journal.py
jetconf/nacm.py
jetconf/op_internal.py
jetconf/rest_server.py
jetconf-0.3.6.dist-info/LICENSE
jetconf-0.3.6.dist-info/METADATA
jetconf-0.3.6.dist-info/WHEEL
jetconf-0.3.6.dist-info/entry_points.txt
jetconf-0.3.6.dist-info/top_level.txt
jetconf-0.3.6.dist-info/RECORD
