Metadata-Version: 2.1
Name: jetconf
Version: 0.3.6
Summary: Pure Python implementation of the RESTCONF protocol
Home-page: https://github.com/CZ-NIC/jetconf
Author: Ales Mrazek
Author-email: ales.mrazek@nic.cz
License: UNKNOWN
Keywords: restconf,yang,data model,configuration,json
Platform: UNKNOWN
Classifier: Programming Language :: Python
Classifier: Programming Language :: Python :: 3.5
Classifier: Development Status :: 3 - Alpha
Classifier: Intended Audience :: System Administrators
Classifier: Intended Audience :: Telecommunications Industry
Classifier: License :: OSI Approved :: GNU General Public License v3 (GPLv3)
Classifier: Operating System :: OS Independent
Classifier: Topic :: System :: Monitoring
Classifier: Topic :: System :: Systems Administration
Requires-Dist: yangson
Requires-Dist: h2
Requires-Dist: colorlog
Requires-Dist: pyaml
Requires-Dist: pytz
